mnt/__init__.py
mnt/bench/__init__.py
mnt/bench/backend.py
mnt/bench/main.py
mnt/bench/py.typed
mnt/bench/static/2ddwave.png
mnt/bench/static/abstraction_level.png
mnt/bench/static/clocking_scheme.png
mnt/bench/static/esr.png
mnt/bench/static/favicon.ico
mnt/bench/static/gate_library.png
mnt/bench/static/mnt_dark.svg
mnt/bench/static/mntbench_technical_report.pdf
mnt/bench/static/optimization_algorithm.png
mnt/bench/static/physical_design_algorithm.png
mnt/bench/static/res.png
mnt/bench/static/row.png
mnt/bench/static/tum_logo.svg
mnt/bench/static/use.png
mnt/bench/static/files/MNTBench_all.zip
mnt/bench/static/files/layout_dimensions.json
mnt/bench/templates/description.html
mnt/bench/templates/error.html
mnt/bench/templates/index.html
mnt/bench/templates/legal.html
mnt.bench-0.2.7.dist-info/LICENSE
mnt.bench-0.2.7.dist-info/METADATA
mnt.bench-0.2.7.dist-info/WHEEL
mnt.bench-0.2.7.dist-info/entry_points.txt
mnt.bench-0.2.7.dist-info/top_level.txt
mnt.bench-0.2.7.dist-info/RECORD
