Metadata-Version: 2.1
Name: mnt.bench
Version: 0.2.7
Summary: MNT Bench - An MNT tool for Benchmarking FCN circuits
Author-email: Simon Hofmann <simon.t.hofmann@tum.de>
License: MIT License
Project-URL: Homepage, https://github.com/cda-tum/mntbench
Project-URL: Bug Tracker, https://github.com/cda-tum/mntbench/issues
Project-URL: Discussions, https://github.com/cda-tum/mntbench/discussions
Project-URL: Research, https://www.cda.cit.tum.de/research/fcn/
Keywords: MNT,field-coupled nanocomputing,benchmarking,performance,testing
Classifier: Development Status :: 4 - Beta
Classifier: Intended Audience :: Developers
Classifier: License :: OSI Approved :: MIT License
Classifier: Operating System :: Microsoft :: Windows
Classifier: Operating System :: MacOS
Classifier: Operating System :: POSIX :: Linux
Classifier: Programming Language :: Python :: 3 :: Only
Classifier: Programming Language :: Python :: 3.8
Classifier: Programming Language :: Python :: 3.9
Classifier: Programming Language :: Python :: 3.10
Classifier: Programming Language :: Python :: 3.11
Classifier: Intended Audience :: Science/Research
Classifier: Natural Language :: English
Classifier: Topic :: Scientific/Engineering :: Electronic Design Automation (EDA)
Requires-Python: >=3.8
License-File: LICENSE
Requires-Dist: pandas >=1.0.0
Requires-Dist: flask >=2.0.0
Requires-Dist: networkx >=2.0.0
Requires-Dist: pyscf >=2.3.0
Requires-Dist: packaging >=21.0
Requires-Dist: tqdm >=4.0.0
Requires-Dist: joblib >=1.3.0
Requires-Dist: requests >=2.31.0
Requires-Dist: openpyxl >=3.1.2
Requires-Dist: humanize >=4.9.0
Requires-Dist: importlib-metadata >=3.6 ; python_version < "3.10"
Requires-Dist: importlib-resources >=5.9 ; python_version < "3.10"
Provides-Extra: coverage
Requires-Dist: mnt.bench[test] ; extra == 'coverage'
Requires-Dist: pytest-cov[toml] ; extra == 'coverage'
Provides-Extra: dev
Requires-Dist: mnt.bench[coverage,docs] ; extra == 'dev'
Provides-Extra: docs
Requires-Dist: furo >=2023.08.17 ; extra == 'docs'
Requires-Dist: sphinx ~=7.0 ; extra == 'docs'
Requires-Dist: myst-parser >=0.13 ; extra == 'docs'
Requires-Dist: setuptools-scm >=7 ; extra == 'docs'
Requires-Dist: sphinx-copybutton ; extra == 'docs'
Requires-Dist: sphinx-design ; extra == 'docs'
Requires-Dist: sphinxext-opengraph ; extra == 'docs'
Provides-Extra: test
Requires-Dist: pytest >=7.2 ; extra == 'test'
